githubguard/__init__.py
githubguard/core.py
githubguard-0.1.1.dist-info/licenses/LICENSE
githubguard-0.1.1.dist-info/METADATA
githubguard-0.1.1.dist-info/WHEEL
githubguard-0.1.1.dist-info/top_level.txt
githubguard-0.1.1.dist-info/RECORD
