Metadata-Version: 2.4
Name: GitHubGuard
Version: 0.1.1
Summary: Automatically create GitHub issues from Python scripts.
Home-page: https://github.com/Xehia/GitHubGuard
Author: Matteo
Classifier: Programming Language :: Python :: 3
Classifier: License :: OSI Approved :: MIT License
Classifier: Operating System :: OS Independent
Requires-Python: >=3.8
License-File: LICENSE
Requires-Dist: requests
Dynamic: author
Dynamic: classifier
Dynamic: description
Dynamic: description-content-type
Dynamic: home-page
Dynamic: license-file
Dynamic: requires-dist
Dynamic: requires-python
Dynamic: summary
